can_cando/CANdo.py
can_cando/CANdoImport.py
can_cando/CANdoTest.py
can_cando/__init__.py
can_cando/py.typed
python_can_cando-1.0.8.dist-info/licenses/LICENSE.txt
python_can_cando-1.0.8.dist-info/METADATA
python_can_cando-1.0.8.dist-info/WHEEL
python_can_cando-1.0.8.dist-info/entry_points.txt
python_can_cando-1.0.8.dist-info/top_level.txt
python_can_cando-1.0.8.dist-info/RECORD
