Metadata-Version: 2.4
Name: python-can-cando
Version: 1.0.8
Summary: python-can interface for Netronics CANdo and CANdoISO devices
Author: Riccardo Belli
License: LGPL v3
Project-URL: Documentation, https://github.com/belliriccardo/python-can-cando#readme
Project-URL: Issues, https://github.com/belliriccardo/python-can-cando/issues
Project-URL: Source, https://github.com/belliriccardo/python-can-cando
Project-URL: Homepage, https://github.com/belliriccardo/python-can-cando
Project-URL: PersonalHomepage, https://www.riccardobelli.it
Keywords: python-can,CAN,CANbus,netronics,cando,candoiso
Classifier: Programming Language :: Python
Classifier: Programming Language :: Python :: 3.7
Classifier: Programming Language :: Python :: 3.8
Classifier: Programming Language :: Python :: 3.9
Classifier: Programming Language :: Python :: 3.10
Classifier: Programming Language :: Python :: 3.11
Classifier: Programming Language :: Python :: 3.12
Classifier: Programming Language :: Python :: Implementation :: CPython
Classifier: Topic :: Software Development :: Embedded Systems
Classifier: Topic :: Software Development :: Embedded Systems :: Controller Area Network (CAN)
Classifier: Typing :: Typed
Classifier: Operating System :: Microsoft :: Windows
Classifier: License :: OSI Approved :: GNU Lesser General Public License v3 (LGPLv3)
Classifier: Intended Audience :: Developers
Requires-Python: >=3.7
License-File: LICENSE.txt
Requires-Dist: python-can==4.*
Provides-Extra: dev
Requires-Dist: ruff==0.7.2; extra == "dev"
Dynamic: license-file
